MANIFEST.in
README.md
setup.py
bin/stm
ssh_tunnel_manager/__init__.py
ssh_tunnel_manager/stm.py
ssh_tunnel_manager/version.py
ssh_tunnel_manager.egg-info/PKG-INFO
ssh_tunnel_manager.egg-info/SOURCES.txt
ssh_tunnel_manager.egg-info/dependency_links.txt
ssh_tunnel_manager.egg-info/requires.txt
ssh_tunnel_manager.egg-info/top_level.txt
ssh_tunnel_manager/conf/default_config.yml
ssh_tunnel_manager/conf/default_dnsmasq-stm.conf