Metadata-Version: 1.1
Name: ssh-tunnel-manager
Version: 1.0.0rc1
Summary: An utility to manage your SSH tunnels
Home-page: https://github.com/hmartinet/ssh-tunnel-manager
Author: Hervé Martinet
Author-email: herve.martinet@gmail.com
License: UNKNOWN
Platform: UNKNOWN
Classifier: Programming Language :: Python
Classifier: Development Status :: 4 - Beta
Classifier: License :: OSI Approved :: GNU General Public License v3 (GPLv3)
Classifier: Natural Language :: English
Classifier: Operating System :: POSIX :: Linux
Classifier: Programming Language :: Python :: 3
Classifier: Topic :: System :: Networking
